plepy/PLEpy.py
plepy/__init__.py
plepy/helper.py
plepy-1.0.dist-info/METADATA
plepy-1.0.dist-info/WHEEL
plepy-1.0.dist-info/top_level.txt
plepy-1.0.dist-info/RECORD
