Metadata-Version: 2.1
Name: plepy
Version: 1.0
Summary: Identifiability tool using profile likelihood that interfaces with Pyomo
Home-page: UNKNOWN
Author: Monica Shapiro
Author-email: monshapiro@gmail.com
License: UNKNOWN
Platform: UNKNOWN
Requires-Dist: numpy
Requires-Dist: pyomo
Requires-Dist: scipy
Requires-Dist: matplotlib
Requires-Dist: seaborn
